subprocess_check/__init__.py
subprocess_check/_util.py
subprocess_check-0.1.0.dist-info/LICENSE.txt
subprocess_check-0.1.0.dist-info/WHEEL
subprocess_check-0.1.0.dist-info/METADATA
subprocess_check-0.1.0.dist-info/RECORD
