Metadata-Version: 2.1
Name: subprocess-check
Version: 0.1.0
Summary: subprocess wrapper that shows sub-process stdout/stderr in error text.
Home-page: https://github.com/chrahunt/subprocess-check
License: MIT
Author: Chris Hunt
Author-email: chrahunt@gmail.com
Requires-Python: >=3.7.0
Classifier: Development Status :: 3 - Alpha
Classifier: Intended Audience :: Developers
Classifier: License :: OSI Approved :: MIT License
Classifier: Programming Language :: Python :: 3
Classifier: Programming Language :: Python :: 3 :: Only
Requires-Dist: pytest ; extra == "test"
Provides-Extra: test
